InsightBoard/__init__.py
InsightBoard/__main__.py
InsightBoard/app.py
InsightBoard/utils.py
InsightBoard/version.py
InsightBoard/config/__init__.py
InsightBoard/config/config.py
InsightBoard/database/__init__.py
InsightBoard/database/database.py
InsightBoard/pages/data.py
InsightBoard/pages/home.py
InsightBoard/pages/reports.py
InsightBoard/pages/settings.py
InsightBoard/pages/upload.py
InsightBoard/parsers/__init__.py
InsightBoard/project/__init__.py
InsightBoard/project/project.py
InsightBoard-0.1.4.dist-info/LICENSE
InsightBoard-0.1.4.dist-info/METADATA
InsightBoard-0.1.4.dist-info/WHEEL
InsightBoard-0.1.4.dist-info/entry_points.txt
InsightBoard-0.1.4.dist-info/top_level.txt
InsightBoard-0.1.4.dist-info/RECORD
