Metadata-Version: 2.1
Name: InsightBoard
Version: 0.1.4
Summary: InsightBoard for data parsing and report generation
Requires-Python: >=3.11
License-File: LICENSE
Requires-Dist: dash >=2.18.1
Requires-Dist: dash-table >=5.0.0
Requires-Dist: pandas >=2.2.3
Requires-Dist: dash-bootstrap-components >=1.6.0
Requires-Dist: pyarrow >=17.0.0
Requires-Dist: openpyxl >=3.1.5
Requires-Dist: jsonschema >=4.23.0
Requires-Dist: dash-dangerously-set-inner-html >=0.0.2
Requires-Dist: tomli-w >=1.0.0
Requires-Dist: waitress >=3.0.0
Requires-Dist: cachetools >=5.5.0
